mistery/__init__.py
mistery-0.0.3.dist-info/METADATA
mistery-0.0.3.dist-info/WHEEL
mistery-0.0.3.dist-info/licenses/LICENSE
mistery-0.0.3.dist-info/RECORD
