Metadata-Version: 2.1
Name: mistery
Version: 0.0.3
Summary: Python module for retrieving data from the MESA Isochrones and Stellar Tracks (MIST) database of stellar models.
Project-URL: Homepage, https://warrickball.gitlab.io/mistery
Project-URL: Bug Tracker, https://gitlab.com/warrickball/mistery/issues
Author: Warrick Ball
License-File: LICENSE
Classifier: License :: OSI Approved :: MIT License
Classifier: Operating System :: OS Independent
Classifier: Programming Language :: Python :: 3
Requires-Python: >=3.7
Requires-Dist: numpy
Requires-Dist: requests
